git_hours/main.py
git_hours-0.1.3.dist-info/entry_points.txt
git_hours-0.1.3.dist-info/WHEEL
git_hours-0.1.3.dist-info/METADATA
git_hours-0.1.3.dist-info/RECORD
