Metadata-Version: 2.1
Name: git-hours
Version: 0.1.3
Summary: Estimate time spent on a git repository 
License: GPL
Author: Stefane Fermigier
Author-email: sf@abilian.com
Requires-Python: >=3.10,<4.0
Classifier: License :: Other/Proprietary License
Classifier: Programming Language :: Python :: 3
Classifier: Programming Language :: Python :: 3.10
Requires-Dist: GitPython (>=3.1.28,<4.0.0)
Requires-Dist: devtools (>=0.9.0,<0.10.0)
Requires-Dist: pydash (>=5.1.1,<6.0.0)
